todocom/__init__.py
todocom/__main__.py
todocom/cli.py
todocom/comments.py
todocom/tokenize.py
todocom/utils.py
todocom-0.2.9.dist-info/entry_points.txt
todocom-0.2.9.dist-info/LICENSE
todocom-0.2.9.dist-info/WHEEL
todocom-0.2.9.dist-info/METADATA
todocom-0.2.9.dist-info/RECORD
