Metadata-Version: 2.1
Name: todocom
Version: 0.2.9
Summary: CLI to retrieve a list of all TODO comments in the code
Home-page: https://github.com/avivfaraj/todocom
License: GPLv3
Keywords: todo,todo-list,todo-comments,cli
Author: avivfaraj
Author-email: avivfaraj4@gmail.com
Requires-Python: >=3.10,<4.0
Classifier: License :: OSI Approved :: GNU General Public License v3 (GPLv3)
Classifier: License :: Other/Proprietary License
Classifier: Operating System :: OS Independent
Classifier: Programming Language :: Python :: 3
Classifier: Programming Language :: Python :: 3.10
Classifier: Programming Language :: Python :: 3
Project-URL: Bug Tracker, https://github.com/avivfaraj/todocom/issues
Project-URL: Documentation, https://github.com/avivfaraj/todocom
Project-URL: Repository, https://github.com/avivfaraj/todocom
